numeration_system/__init__.py
numeration_system/numeration_system.py
numeration_system-0.2.6.dist-info/LICENSE
numeration_system-0.2.6.dist-info/METADATA
numeration_system-0.2.6.dist-info/WHEEL
numeration_system-0.2.6.dist-info/top_level.txt
numeration_system-0.2.6.dist-info/RECORD
