Metadata-Version: 2.2
Name: numeration_system
Version: 0.2.6
Summary: A non-professional library created to provide value conversion functions in the number system.
Author-email: Lucas Maciel <lalucasforte56@gmail.com>
License: Copyright (c) 2025 Lucas Maciel
Project-URL: Homepage, https://github.com/luca-maciel/calculadora_sistema_numera-o
Requires-Python: >=3.7
License-File: LICENSE
